README.md
setup.py
hexson/__init__.py
hexson/dumpper.py
hexson/exceptions.py
hexson/parser.py
hexson/serializer.py
hexson.egg-info/PKG-INFO
hexson.egg-info/SOURCES.txt
hexson.egg-info/dependency_links.txt
hexson.egg-info/top_level.txt
test/test.py