Metadata-Version: 2.1
Name: hexson
Version: 0.0.5
Summary: Json library which enable user to parse and dump data with hex escape
Home-page: https://github.com/wonderqs/hexson
Author: ManchurianClassmate
Author-email: i@listenwhat.com
Maintainer: ManchurianClassmate
Maintainer-email: i@listenwhat.com
License: Apache-2.0
Platform: UNKNOWN
Classifier: Development Status :: 5 - Production/Stable
Classifier: License :: OSI Approved :: Apache Software License
Classifier: Intended Audience :: Developers
Classifier: Operating System :: OS Independent
Classifier: Programming Language :: Python :: 3
Classifier: Programming Language :: Python :: 3.4
Classifier: Programming Language :: Python :: 3.5
Classifier: Programming Language :: Python :: 3.6
Classifier: Programming Language :: Python :: 3.7
Classifier: Programming Language :: Python :: 3.8
Classifier: Programming Language :: Python :: Implementation :: CPython
Classifier: Programming Language :: Python :: Implementation :: PyPy
Requires-Python: !=3.0.*, !=3.1.*, !=3.2.*, !=3.3.*, <4
